LICENSE
README.md
pyproject.toml
setup.py
carefree_cython.egg-info/PKG-INFO
carefree_cython.egg-info/SOURCES.txt
carefree_cython.egg-info/dependency_links.txt
carefree_cython.egg-info/requires.txt
carefree_cython.egg-info/top_level.txt
cfc/__init__.py
cfc/api.py
cfc/cython_substitute.py
cfc/cython_utils.c
cfc/cython_utils.pyx
cfc/cython_wrappers.py
cfc/stat.py