Metadata-Version: 2.1
Name: carefree-cython
Version: 0.1.0
Summary: Some commonly used cython functions
Home-page: https://github.com/carefree0910/carefree-cython
Author: carefree0910
Author-email: syameimaru.saki@gmail.com
License: UNKNOWN
Download-URL: https://github.com/carefree0910/carefree-cython/archive/v0.1.0.tar.gz
Keywords: python numpy data-science
Platform: UNKNOWN
License-File: LICENSE
